nusacrowd/__init__.py
nusacrowd/config_helper.py
nusacrowd/nusa_datasets/__init__.py
nusacrowd/nusa_datasets/barasa/__init__.py
nusacrowd/nusa_datasets/barasa/barasa.py
nusacrowd/nusa_datasets/bible_en_id/__init__.py
nusacrowd/nusa_datasets/bible_en_id/bible_en_id.py
nusacrowd/nusa_datasets/bible_jv_id/__init__.py
nusacrowd/nusa_datasets/bible_jv_id/bible_jv_id.py
nusacrowd/nusa_datasets/bible_su_id/__init__.py
nusacrowd/nusa_datasets/bible_su_id/bible_su_id.py
nusacrowd/nusa_datasets/casa/__init__.py
nusacrowd/nusa_datasets/casa/casa.py
nusacrowd/nusa_datasets/cc100/__init__.py
nusacrowd/nusa_datasets/cc100/cc100.py
nusacrowd/nusa_datasets/cod/__init__.py
nusacrowd/nusa_datasets/cod/cod.py
nusacrowd/nusa_datasets/code_mixed_jv_id/__init__.py
nusacrowd/nusa_datasets/code_mixed_jv_id/code_mixed_jv_id.py
nusacrowd/nusa_datasets/covost2/__init__.py
nusacrowd/nusa_datasets/covost2/covost2.py
nusacrowd/nusa_datasets/cvss/__init__.py
nusacrowd/nusa_datasets/cvss/cvss.py
nusacrowd/nusa_datasets/emot/__init__.py
nusacrowd/nusa_datasets/emot/emot.py
nusacrowd/nusa_datasets/emotcmt/__init__.py
nusacrowd/nusa_datasets/emotcmt/emotcmt.py
nusacrowd/nusa_datasets/emotion_id_opinion/__init__.py
nusacrowd/nusa_datasets/emotion_id_opinion/emotion_id_opinion.py
nusacrowd/nusa_datasets/facqa/__init__.py
nusacrowd/nusa_datasets/facqa/facqa.py
nusacrowd/nusa_datasets/facqa/utils/__init__.py
nusacrowd/nusa_datasets/facqa/utils/facqa_utils.py
nusacrowd/nusa_datasets/hoasa/__init__.py
nusacrowd/nusa_datasets/hoasa/hoasa.py
nusacrowd/nusa_datasets/id_abusive/__init__.py
nusacrowd/nusa_datasets/id_abusive/id_abusive.py
nusacrowd/nusa_datasets/id_abusive_news_comment/__init__.py
nusacrowd/nusa_datasets/id_abusive_news_comment/id_abusive_news_comment.py
nusacrowd/nusa_datasets/id_am2ico/__init__.py
nusacrowd/nusa_datasets/id_am2ico/id_am2ico.py
nusacrowd/nusa_datasets/id_clickbait/__init__.py
nusacrowd/nusa_datasets/id_clickbait/id_clickbait.py
nusacrowd-0.1.4.dist-info/LICENSE
nusacrowd-0.1.4.dist-info/METADATA
nusacrowd-0.1.4.dist-info/WHEEL
nusacrowd-0.1.4.dist-info/top_level.txt
nusacrowd-0.1.4.dist-info/RECORD
