Metadata-Version: 2.1
Name: nusacrowd
Version: 0.1.4
Requires-Python: >=3.7
License-File: LICENSE
Requires-Dist: loguru >=0.5.3
Requires-Dist: bioc >=1.3.7
Requires-Dist: pandas >=1.3.3
Requires-Dist: numpy >=1.20
Requires-Dist: datasets >=2.2.0
Requires-Dist: black ~=22.0
Requires-Dist: flake8 >=3.8.3
Requires-Dist: isort >=5.0.0
Requires-Dist: aiohttp >=3.8.1
Requires-Dist: pre-commit >=2.19.0
Requires-Dist: jsonlines >=3.1.0
Requires-Dist: torchaudio >=0.11
Requires-Dist: soundfile
Requires-Dist: librosa
Requires-Dist: nltk
Requires-Dist: zstandard
Requires-Dist: ffmpeg
Requires-Dist: conllu
Requires-Dist: openpyxl
Requires-Dist: translate-toolkit >=3.7.3
Requires-Dist: typing-extensions
Provides-Extra: deploy
Requires-Dist: build ==0.7.0 ; extra == 'deploy'
Requires-Dist: twine ==4.0.0 ; extra == 'deploy'
Provides-Extra: dev
Requires-Dist: black <22.2.0,>=22.1.0 ; extra == 'dev'
Requires-Dist: flake8 <3.9.0,>=3.8.3 ; extra == 'dev'
Requires-Dist: isort <5.1.0,>=5.0.0 ; extra == 'dev'
Provides-Extra: ipython
Requires-Dist: ipython ; extra == 'ipython'
